{"ticker": "O:SPY250307P00551000", "queryCount": 149, "resultsCount": 149, "adjusted": true, "results": [{"v": 13, "vw": 0.0769, "o": 0.09, "c": 0.08, "h": 0.09, "l": 0.07, "t": 1741357800000, "n": 9}, {"v": 13, "vw": 0.07, "o": 0.07, "c": 0.07, "h": 0.07, "l": 0.07, "t": 1741357860000, "n": 2}, {"v": 3, "vw": 0.0567, "o": 0.06, "c": 0.06, "h": 0.06, "l": 0.05, "t": 1741357920000, "n": 3}, {"v": 64, "vw": 0.0506, "o": 0.06, "c": 0.05, "h": 0.06, "l": 0.05, "t": 1741357980000, "n": 6}, {"v": 37, "vw": 0.0414, "o": 0.04, "c": 0.04, "h": 0.05, "l": 0.04, "t": 1741358040000, "n": 10}, {"v": 195, "vw": 0.0417, "o": 0.05, "c": 0.04, "h": 0.05, "l": 0.03, "t": 1741358100000, "n": 12}, {"v": 36, "vw": 0.0383, "o": 0.03, "c": 0.05, "h": 0.05, "l": 0.03, "t": 1741358160000, "n": 15}, {"v": 184, "vw": 0.0424, "o": 0.04, "c": 0.05, "h": 0.05, "l": 0.04, "t": 1741358220000, "n": 12}, {"v": 3, "vw": 0.04, "o": 0.04, "c": 0.04, "h": 0.04, "l": 0.04, "t": 1741358280000, "n": 1}, {"v": 5, "vw": 0.04, "o": 0.04, "c": 0.04, "h": 0.04, "l": 0.04, "t": 1741358340000, "n": 3}, {"v": 2, "vw": 0.03, "o": 0.03, "c": 0.03, "h": 0.03, "l": 0.03, "t": 1741358400000, "n": 1}, {"v": 106, "vw": 0.04, "o": 0.04, "c": 0.04, "h": 0.04, "l": 0.04, "t": 1741358460000, "n": 6}, {"v": 120, "vw": 0.03, "o": 0.03, "c": 0.03, "h": 0.03, "l": 0.03, "t": 1741358520000, "n": 5}, {"v": 1, "vw": 0.03, "o": 0.03, "c": 0.03, "h": 0.03, "l": 0.03, "t": 1741358580000, "n": 1}, {"v": 12, "vw": 0.0225, "o": 0.02, "c": 0.02, "h": 0.03, "l": 0.02, "t": 1741358640000, "n": 6}, {"v": 6, "vw": 0.03, "o": 0.03, "c": 0.03, "h": 0.03, "l": 0.03, "t": 1741358700000, "n": 4}, {"v": 1, "vw": 0.03, "o": 0.03, "c": 0.03, "h": 0.03, "l": 0.03, "t": 1741358760000, "n": 1}, {"v": 5, "vw": 0.022, "o": 0.02, "c": 0.02, "h": 0.03, "l": 0.02, "t": 1741358820000, "n": 4}, {"v": 11, "vw": 0.0209, "o": 0.03, "c": 0.02, "h": 0.03, "l": 0.02, "t": 1741358880000, "n": 2}, {"v": 1, "vw": 0.02, "o": 0.02, "c": 0.02, "h": 0.02, "l": 0.02, "t": 1741358940000, "n": 1}, {"v": 7, "vw": 0.0286, "o": 0.03, "c": 0.03, "h": 0.03, "l": 0.02, "t": 1741359000000, "n": 3}, {"v": 2, "vw": 0.02, "o": 0.02, "c": 0.02, "h": 0.02, "l": 0.02, "t": 1741359120000, "n": 1}, {"v": 2, "vw": 0.025, "o": 0.03, "c": 0.02, "h": 0.03, "l": 0.02, "t": 1741359180000, "n": 2}, {"v": 40, "vw": 0.0275, "o": 0.02, "c": 0.03, "h": 0.03, "l": 0.02, "t": 1741359240000, "n": 7}, {"v": 1, "vw": 0.02, "o": 0.02, "c": 0.02, "h": 0.02, "l": 0.02, "t": 1741359360000, "n": 1}, {"v": 14, "vw": 0.03, "o": 0.03, "c": 0.03, "h": 0.03, "l": 0.03, "t": 1741359420000, "n": 2}, {"v": 2, "vw": 0.03, "o": 0.03, "c": 0.03, "h": 0.03, "l": 0.03, "t": 1741359480000, "n": 1}, {"v": 24, "vw": 0.0388, "o": 0.04, "c": 0.03, "h": 0.04, "l": 0.03, "t": 1741359600000, "n": 7}, {"v": 9, "vw": 0.04, "o": 0.04, "c": 0.04, "h": 0.04, "l": 0.04, "t": 1741359660000, "n": 3}, {"v": 55, "vw": 0.0282, "o": 0.03, "c": 0.02, "h": 0.03, "l": 0.02, "t": 1741359720000, "n": 8}, {"v": 20, "vw": 0.03, "o": 0.03, "c": 0.03, "h": 0.03, "l": 0.03, "t": 1741359780000, "n": 1}, {"v": 5, "vw": 0.03, "o": 0.03, "c": 0.03, "h": 0.03, "l": 0.03, "t": 1741359840000, "n": 1}, {"v": 20, "vw": 0.03, "o": 0.03, "c": 0.03, "h": 0.03, "l": 0.03, "t": 1741359960000, "n": 1}, {"v": 16, "vw": 0.02, "o": 0.02, "c": 0.02, "h": 0.02, "l": 0.02, "t": 1741360080000, "n": 1}, {"v": 11, "vw": 0.03, "o": 0.03, "c": 0.03, "h": 0.03, "l": 0.03, "t": 1741360440000, "n": 2}, {"v": 38, "vw": 0.0303, "o": 0.03, "c": 0.04, "h": 0.04, "l": 0.03, "t": 1741360500000, "n": 3}, {"v": 6, "vw": 0.03, "o": 0.03, "c": 0.03, "h": 0.03, "l": 0.03, "t": 1741360620000, "n": 2}, {"v": 5, "vw": 0.04, "o": 0.04, "c": 0.04, "h": 0.04, "l": 0.04, "t": 1741360680000, "n": 1}, {"v": 64, "vw": 0.03, "o": 0.03, "c": 0.03, "h": 0.03, "l": 0.03, "t": 1741360740000, "n": 5}, {"v": 10, "vw": 0.03, "o": 0.03, "c": 0.03, "h": 0.03, "l": 0.03, "t": 1741360860000, "n": 1}, {"v": 7, "vw": 0.03, "o": 0.03, "c": 0.03, "h": 0.03, "l": 0.03, "t": 1741361100000, "n": 7}, {"v": 1, "vw": 0.03, "o": 0.03, "c": 0.03, "h": 0.03, "l": 0.03, "t": 1741361280000, "n": 1}, {"v": 12, "vw": 0.0292, "o": 0.02, "c": 0.03, "h": 0.03, "l": 0.02, "t": 1741361340000, "n": 2}, {"v": 26, "vw": 0.0342, "o": 0.03, "c": 0.04, "h": 0.04, "l": 0.03, "t": 1741361460000, "n": 7}, {"v": 48, "vw": 0.0498, "o": 0.04, "c": 0.05, "h": 0.05, "l": 0.04, "t": 1741361520000, "n": 6}, {"v": 24, "vw": 0.0446, "o": 0.05, "c": 0.04, "h": 0.05, "l": 0.04, "t": 1741361580000, "n": 6}, {"v": 50, "vw": 0.04, "o": 0.04, "c": 0.04, "h": 0.04, "l": 0.04, "t": 1741361640000, "n": 5}, {"v": 62, "vw": 0.0402, "o": 0.04, "c": 0.04, "h": 0.05, "l": 0.04, "t": 1741361700000, "n": 3}, {"v": 2, "vw": 0.05, "o": 0.05, "c": 0.05, "h": 0.05, "l": 0.05, "t": 1741361760000, "n": 2}, {"v": 16, "vw": 0.0431, "o": 0.05, "c": 0.04, "h": 0.05, "l": 0.04, "t": 1741361820000, "n": 4}, {"v": 307, "vw": 0.05, "o": 0.05, "c": 0.05, "h": 0.05, "l": 0.04, "t": 1741361880000, "n": 9}, {"v": 26, "vw": 0.0419, "o": 0.04, "c": 0.04, "h": 0.05, "l": 0.04, "t": 1741361940000, "n": 11}, {"v": 321, "vw": 0.05, "o": 0.04, "c": 0.05, "h": 0.05, "l": 0.04, "t": 1741362000000, "n": 5}, {"v": 1316, "vw": 0.05, "o": 0.05, "c": 0.05, "h": 0.06, "l": 0.05, "t": 1741362060000, "n": 26}, {"v": 59, "vw": 0.05, "o": 0.05, "c": 0.05, "h": 0.05, "l": 0.05, "t": 1741362120000, "n": 3}, {"v": 4, "vw": 0.0425, "o": 0.04, "c": 0.04, "h": 0.05, "l": 0.04, "t": 1741362180000, "n": 3}, {"v": 8, "vw": 0.0413, "o": 0.04, "c": 0.05, "h": 0.05, "l": 0.04, "t": 1741362240000, "n": 4}, {"v": 13, "vw": 0.0446, "o": 0.04, "c": 0.04, "h": 0.05, "l": 0.04, "t": 1741362300000, "n": 6}, {"v": 3, "vw": 0.0333, "o": 0.03, "c": 0.04, "h": 0.04, "l": 0.03, "t": 1741362360000, "n": 3}, {"v": 19, "vw": 0.04, "o": 0.04, "c": 0.04, "h": 0.04, "l": 0.04, "t": 1741362420000, "n": 3}, {"v": 21, "vw": 0.0205, "o": 0.03, "c": 0.02, "h": 0.03, "l": 0.02, "t": 1741362540000, "n": 4}, {"v": 503, "vw": 0.04, "o": 0.04, "c": 0.04, "h": 0.04, "l": 0.04, "t": 1741362660000, "n": 4}, {"v": 100, "vw": 0.05, "o": 0.05, "c": 0.05, "h": 0.05, "l": 0.05, "t": 1741362780000, "n": 4}, {"v": 8, "vw": 0.0363, "o": 0.04, "c": 0.03, "h": 0.04, "l": 0.03, "t": 1741362960000, "n": 4}, {"v": 11, "vw": 0.04, "o": 0.04, "c": 0.04, "h": 0.04, "l": 0.04, "t": 1741363020000, "n": 1}, {"v": 1, "vw": 0.04, "o": 0.04, "c": 0.04, "h": 0.04, "l": 0.04, "t": 1741363320000, "n": 1}, {"v": 1, "vw": 0.05, "o": 0.05, "c": 0.05, "h": 0.05, "l": 0.05, "t": 1741363560000, "n": 1}, {"v": 4, "vw": 0.05, "o": 0.05, "c": 0.05, "h": 0.05, "l": 0.05, "t": 1741363740000, "n": 2}, {"v": 1, "vw": 0.04, "o": 0.04, "c": 0.04, "h": 0.04, "l": 0.04, "t": 1741363860000, "n": 1}, {"v": 1, "vw": 0.04, "o": 0.04, "c": 0.04, "h": 0.04, "l": 0.04, "t": 1741364220000, "n": 1}, {"v": 2, "vw": 0.045, "o": 0.05, "c": 0.04, "h": 0.05, "l": 0.04, "t": 1741364340000, "n": 2}, {"v": 13, "vw": 0.0423, "o": 0.04, "c": 0.05, "h": 0.05, "l": 0.04, "t": 1741364400000, "n": 5}, {"v": 743, "vw": 0.0502, "o": 0.05, "c": 0.05, "h": 0.06, "l": 0.05, "t": 1741364760000, "n": 11}, {"v": 1, "vw": 0.04, "o": 0.04, "c": 0.04, "h": 0.04, "l": 0.04, "t": 1741364820000, "n": 1}, {"v": 6, "vw": 0.0417, "o": 0.05, "c": 0.04, "h": 0.05, "l": 0.04, "t": 1741364880000, "n": 2}, {"v": 1, "vw": 0.05, "o": 0.05, "c": 0.05, "h": 0.05, "l": 0.05, "t": 1741364940000, "n": 1}, {"v": 3, "vw": 0.0467, "o": 0.05, "c": 0.04, "h": 0.05, "l": 0.04, "t": 1741365000000, "n": 2}, {"v": 5, "vw": 0.04, "o": 0.04, "c": 0.04, "h": 0.04, "l": 0.04, "t": 1741365060000, "n": 1}, {"v": 31, "vw": 0.03, "o": 0.03, "c": 0.03, "h": 0.03, "l": 0.03, "t": 1741365180000, "n": 4}, {"v": 12, "vw": 0.0308, "o": 0.04, "c": 0.03, "h": 0.04, "l": 0.03, "t": 1741365240000, "n": 3}, {"v": 1, "vw": 0.04, "o": 0.04, "c": 0.04, "h": 0.04, "l": 0.04, "t": 1741365360000, "n": 1}, {"v": 4, "vw": 0.035, "o": 0.04, "c": 0.04, "h": 0.04, "l": 0.03, "t": 1741365480000, "n": 3}, {"v": 21, "vw": 0.04, "o": 0.04, "c": 0.04, "h": 0.04, "l": 0.04, "t": 1741365600000, "n": 2}, {"v": 8, "vw": 0.0488, "o": 0.04, "c": 0.05, "h": 0.05, "l": 0.04, "t": 1741365660000, "n": 4}, {"v": 1, "vw": 0.04, "o": 0.04, "c": 0.04, "h": 0.04, "l": 0.04, "t": 1741365780000, "n": 1}, {"v": 2, "vw": 0.035, "o": 0.04, "c": 0.03, "h": 0.04, "l": 0.03, "t": 1741365840000, "n": 2}, {"v": 1, "vw": 0.03, "o": 0.03, "c": 0.03, "h": 0.03, "l": 0.03, "t": 1741365960000, "n": 1}, {"v": 4, "vw": 0.04, "o": 0.04, "c": 0.04, "h": 0.04, "l": 0.04, "t": 1741366020000, "n": 2}, {"v": 75, "vw": 0.03, "o": 0.03, "c": 0.03, "h": 0.03, "l": 0.03, "t": 1741366140000, "n": 1}, {"v": 4, "vw": 0.035, "o": 0.04, "c": 0.03, "h": 0.04, "l": 0.03, "t": 1741366200000, "n": 2}, {"v": 20, "vw": 0.038, "o": 0.04, "c": 0.03, "h": 0.04, "l": 0.03, "t": 1741366380000, "n": 4}, {"v": 9, "vw": 0.0311, "o": 0.03, "c": 0.04, "h": 0.04, "l": 0.03, "t": 1741366440000, "n": 3}, {"v": 3, "vw": 0.0333, "o": 0.03, "c": 0.03, "h": 0.04, "l": 0.03, "t": 1741366500000, "n": 3}, {"v": 105, "vw": 0.0305, "o": 0.03, "c": 0.04, "h": 0.04, "l": 0.03, "t": 1741366560000, "n": 5}, {"v": 1, "vw": 0.03, "o": 0.03, "c": 0.03, "h": 0.03, "l": 0.03, "t": 1741366620000, "n": 1}, {"v": 2, "vw": 0.03, "o": 0.03, "c": 0.03, "h": 0.03, "l": 0.03, "t": 1741366800000, "n": 2}, {"v": 1, "vw": 0.02, "o": 0.02, "c": 0.02, "h": 0.02, "l": 0.02, "t": 1741366920000, "n": 1}, {"v": 3, "vw": 0.0233, "o": 0.02, "c": 0.02, "h": 0.03, "l": 0.02, "t": 1741366980000, "n": 3}, {"v": 11, "vw": 0.0227, "o": 0.02, "c": 0.03, "h": 0.03, "l": 0.02, "t": 1741367100000, "n": 8}, {"v": 21, "vw": 0.03, "o": 0.03, "c": 0.03, "h": 0.03, "l": 0.03, "t": 1741367160000, "n": 2}, {"v": 502, "vw": 0.03, "o": 0.03, "c": 0.03, "h": 0.03, "l": 0.03, "t": 1741367220000, "n": 14}, {"v": 6, "vw": 0.03, "o": 0.03, "c": 0.03, "h": 0.03, "l": 0.03, "t": 1741367280000, "n": 3}, {"v": 2, "vw": 0.025, "o": 0.03, "c": 0.02, "h": 0.03, "l": 0.02, "t": 1741367400000, "n": 2}, {"v": 7, "vw": 0.0271, "o": 0.03, "c": 0.02, "h": 0.03, "l": 0.02, "t": 1741367460000, "n": 3}, {"v": 21, "vw": 0.03, "o": 0.03, "c": 0.03, "h": 0.03, "l": 0.03, "t": 1741367520000, "n": 2}, {"v": 2, "vw": 0.025, "o": 0.03, "c": 0.02, "h": 0.03, "l": 0.02, "t": 1741367580000, "n": 2}, {"v": 1, "vw": 0.02, "o": 0.02, "c": 0.02, "h": 0.02, "l": 0.02, "t": 1741367700000, "n": 1}, {"v": 1, "vw": 0.03, "o": 0.03, "c": 0.03, "h": 0.03, "l": 0.03, "t": 1741367820000, "n": 1}, {"v": 12, "vw": 0.0283, "o": 0.03, "c": 0.02, "h": 0.03, "l": 0.02, "t": 1741367880000, "n": 3}, {"v": 2, "vw": 0.02, "o": 0.02, "c": 0.02, "h": 0.02, "l": 0.02, "t": 1741367940000, "n": 1}, {"v": 1, "vw": 0.03, "o": 0.03, "c": 0.03, "h": 0.03, "l": 0.03, "t": 1741368000000, "n": 1}, {"v": 15, "vw": 0.03, "o": 0.03, "c": 0.03, "h": 0.03, "l": 0.03, "t": 1741368120000, "n": 5}, {"v": 1, "vw": 0.02, "o": 0.02, "c": 0.02, "h": 0.02, "l": 0.02, "t": 1741368240000, "n": 1}, {"v": 10, "vw": 0.03, "o": 0.03, "c": 0.03, "h": 0.03, "l": 0.03, "t": 1741368360000, "n": 4}, {"v": 1, "vw": 0.02, "o": 0.02, "c": 0.02, "h": 0.02, "l": 0.02, "t": 1741368600000, "n": 1}, {"v": 13, "vw": 0.0185, "o": 0.02, "c": 0.01, "h": 0.02, "l": 0.01, "t": 1741368780000, "n": 3}, {"v": 11, "vw": 0.0191, "o": 0.01, "c": 0.02, "h": 0.02, "l": 0.01, "t": 1741368840000, "n": 2}, {"v": 3, "vw": 0.01, "o": 0.01, "c": 0.01, "h": 0.01, "l": 0.01, "t": 1741368900000, "n": 1}, {"v": 2, "vw": 0.02, "o": 0.02, "c": 0.02, "h": 0.02, "l": 0.02, "t": 1741368960000, "n": 2}, {"v": 15, "vw": 0.01, "o": 0.01, "c": 0.01, "h": 0.01, "l": 0.01, "t": 1741369140000, "n": 1}, {"v": 2, "vw": 0.01, "o": 0.01, "c": 0.01, "h": 0.01, "l": 0.01, "t": 1741369380000, "n": 1}, {"v": 9, "vw": 0.0189, "o": 0.02, "c": 0.02, "h": 0.02, "l": 0.01, "t": 1741369440000, "n": 3}, {"v": 2, "vw": 0.01, "o": 0.01, "c": 0.01, "h": 0.01, "l": 0.01, "t": 1741369500000, "n": 2}, {"v": 100, "vw": 0.01, "o": 0.01, "c": 0.01, "h": 0.01, "l": 0.01, "t": 1741369620000, "n": 2}, {"v": 1, "vw": 0.01, "o": 0.01, "c": 0.01, "h": 0.01, "l": 0.01, "t": 1741369740000, "n": 1}, {"v": 20, "vw": 0.01, "o": 0.01, "c": 0.01, "h": 0.01, "l": 0.01, "t": 1741369980000, "n": 1}, {"v": 66, "vw": 0.0115, "o": 0.01, "c": 0.01, "h": 0.02, "l": 0.01, "t": 1741370100000, "n": 8}, {"v": 6, "vw": 0.0183, "o": 0.02, "c": 0.01, "h": 0.02, "l": 0.01, "t": 1741370220000, "n": 2}, {"v": 4, "vw": 0.01, "o": 0.01, "c": 0.01, "h": 0.01, "l": 0.01, "t": 1741370280000, "n": 2}, {"v": 4, "vw": 0.0125, "o": 0.01, "c": 0.01, "h": 0.02, "l": 0.01, "t": 1741370400000, "n": 3}, {"v": 1, "vw": 0.01, "o": 0.01, "c": 0.01, "h": 0.01, "l": 0.01, "t": 1741370640000, "n": 1}, {"v": 9, "vw": 0.01, "o": 0.01, "c": 0.01, "h": 0.01, "l": 0.01, "t": 1741370700000, "n": 1}, {"v": 1, "vw": 0.01, "o": 0.01, "c": 0.01, "h": 0.01, "l": 0.01, "t": 1741370760000, "n": 1}, {"v": 9, "vw": 0.01, "o": 0.01, "c": 0.01, "h": 0.01, "l": 0.01, "t": 1741370820000, "n": 4}, {"v": 1, "vw": 0.01, "o": 0.01, "c": 0.01, "h": 0.01, "l": 0.01, "t": 1741370940000, "n": 1}, {"v": 14, "vw": 0.0129, "o": 0.02, "c": 0.01, "h": 0.02, "l": 0.01, "t": 1741371060000, "n": 4}, {"v": 2, "vw": 0.01, "o": 0.01, "c": 0.01, "h": 0.01, "l": 0.01, "t": 1741371120000, "n": 2}, {"v": 1, "vw": 0.01, "o": 0.01, "c": 0.01, "h": 0.01, "l": 0.01, "t": 1741371180000, "n": 1}, {"v": 5, "vw": 0.01, "o": 0.01, "c": 0.01, "h": 0.01, "l": 0.01, "t": 1741372740000, "n": 1}, {"v": 5, "vw": 0.01, "o": 0.01, "c": 0.01, "h": 0.01, "l": 0.01, "t": 1741372860000, "n": 1}, {"v": 5, "vw": 0.01, "o": 0.01, "c": 0.01, "h": 0.01, "l": 0.01, "t": 1741372980000, "n": 1}, {"v": 5, "vw": 0.01, "o": 0.01, "c": 0.01, "h": 0.01, "l": 0.01, "t": 1741373280000, "n": 1}, {"v": 50, "vw": 0.01, "o": 0.01, "c": 0.01, "h": 0.01, "l": 0.01, "t": 1741373580000, "n": 5}, {"v": 5, "vw": 0.01, "o": 0.01, "c": 0.01, "h": 0.01, "l": 0.01, "t": 1741373880000, "n": 1}, {"v": 5, "vw": 0.01, "o": 0.01, "c": 0.01, "h": 0.01, "l": 0.01, "t": 1741374000000, "n": 5}, {"v": 1, "vw": 0.01, "o": 0.01, "c": 0.01, "h": 0.01, "l": 0.01, "t": 1741374060000, "n": 1}, {"v": 3, "vw": 0.01, "o": 0.01, "c": 0.01, "h": 0.01, "l": 0.01, "t": 1741375740000, "n": 1}, {"v": 1, "vw": 0.01, "o": 0.01, "c": 0.01, "h": 0.01, "l": 0.01, "t": 1741379340000, "n": 1}, {"v": 5, "vw": 0.01, "o": 0.01, "c": 0.01, "h": 0.01, "l": 0.01, "t": 1741380180000, "n": 1}], "status": "OK", "request_id": "82c7feb02eba28b340eca3ab3f802728", "count": 149}