{"ticker": "O:SPY220218C00447000", "queryCount": 193, "resultsCount": 193, "adjusted": true, "results": [{"v": 151, "vw": 0.0736, "o": 0.08, "c": 0.07, "h": 0.09, "l": 0.06, "t": 1645194600000, "n": 30}, {"v": 320, "vw": 0.0768, "o": 0.08, "c": 0.08, "h": 0.09, "l": 0.07, "t": 1645194660000, "n": 46}, {"v": 88, "vw": 0.0876, "o": 0.08, "c": 0.08, "h": 0.09, "l": 0.08, "t": 1645194720000, "n": 21}, {"v": 139, "vw": 0.0718, "o": 0.09, "c": 0.08, "h": 0.09, "l": 0.07, "t": 1645194780000, "n": 24}, {"v": 253, "vw": 0.075, "o": 0.07, "c": 0.06, "h": 0.08, "l": 0.06, "t": 1645194840000, "n": 34}, {"v": 88, "vw": 0.0606, "o": 0.06, "c": 0.05, "h": 0.07, "l": 0.05, "t": 1645194900000, "n": 23}, {"v": 73, "vw": 0.0538, "o": 0.05, "c": 0.05, "h": 0.06, "l": 0.05, "t": 1645194960000, "n": 23}, {"v": 58, "vw": 0.0526, "o": 0.06, "c": 0.05, "h": 0.06, "l": 0.05, "t": 1645195020000, "n": 22}, {"v": 54, "vw": 0.0567, "o": 0.06, "c": 0.06, "h": 0.07, "l": 0.05, "t": 1645195080000, "n": 21}, {"v": 23, "vw": 0.0539, "o": 0.06, "c": 0.05, "h": 0.06, "l": 0.05, "t": 1645195140000, "n": 13}, {"v": 95, "vw": 0.0581, "o": 0.05, "c": 0.05, "h": 0.06, "l": 0.05, "t": 1645195200000, "n": 16}, {"v": 288, "vw": 0.0448, "o": 0.05, "c": 0.05, "h": 0.06, "l": 0.04, "t": 1645195260000, "n": 28}, {"v": 211, "vw": 0.0404, "o": 0.04, "c": 0.04, "h": 0.05, "l": 0.04, "t": 1645195320000, "n": 8}, {"v": 315, "vw": 0.0403, "o": 0.04, "c": 0.04, "h": 0.05, "l": 0.04, "t": 1645195380000, "n": 13}, {"v": 17, "vw": 0.0459, "o": 0.04, "c": 0.03, "h": 0.05, "l": 0.03, "t": 1645195440000, "n": 5}, {"v": 470, "vw": 0.0349, "o": 0.03, "c": 0.03, "h": 0.04, "l": 0.03, "t": 1645195500000, "n": 20}, {"v": 26, "vw": 0.0362, "o": 0.04, "c": 0.04, "h": 0.04, "l": 0.03, "t": 1645195560000, "n": 5}, {"v": 129, "vw": 0.0405, "o": 0.04, "c": 0.04, "h": 0.05, "l": 0.04, "t": 1645195620000, "n": 10}, {"v": 865, "vw": 0.0494, "o": 0.04, "c": 0.04, "h": 0.05, "l": 0.04, "t": 1645195680000, "n": 15}, {"v": 86, "vw": 0.036, "o": 0.03, "c": 0.04, "h": 0.05, "l": 0.03, "t": 1645195740000, "n": 14}, {"v": 317, "vw": 0.0415, "o": 0.04, "c": 0.04, "h": 0.05, "l": 0.03, "t": 1645195800000, "n": 29}, {"v": 558, "vw": 0.0402, "o": 0.04, "c": 0.03, "h": 0.05, "l": 0.03, "t": 1645195860000, "n": 20}, {"v": 64, "vw": 0.0473, "o": 0.05, "c": 0.04, "h": 0.05, "l": 0.03, "t": 1645195920000, "n": 5}, {"v": 665, "vw": 0.0409, "o": 0.04, "c": 0.04, "h": 0.05, "l": 0.04, "t": 1645195980000, "n": 17}, {"v": 19, "vw": 0.0463, "o": 0.05, "c": 0.04, "h": 0.05, "l": 0.04, "t": 1645196040000, "n": 5}, {"v": 17, "vw": 0.0441, "o": 0.05, "c": 0.04, "h": 0.05, "l": 0.04, "t": 1645196100000, "n": 8}, {"v": 76, "vw": 0.0407, "o": 0.04, "c": 0.04, "h": 0.05, "l": 0.04, "t": 1645196160000, "n": 11}, {"v": 102, "vw": 0.0421, "o": 0.04, "c": 0.05, "h": 0.05, "l": 0.04, "t": 1645196220000, "n": 6}, {"v": 118, "vw": 0.0408, "o": 0.04, "c": 0.03, "h": 0.05, "l": 0.03, "t": 1645196280000, "n": 9}, {"v": 74, "vw": 0.0343, "o": 0.04, "c": 0.03, "h": 0.04, "l": 0.03, "t": 1645196340000, "n": 11}, {"v": 20, "vw": 0.0395, "o": 0.04, "c": 0.03, "h": 0.04, "l": 0.03, "t": 1645196400000, "n": 4}, {"v": 14, "vw": 0.0314, "o": 0.03, "c": 0.04, "h": 0.04, "l": 0.03, "t": 1645196460000, "n": 4}, {"v": 11, "vw": 0.0364, "o": 0.04, "c": 0.04, "h": 0.04, "l": 0.03, "t": 1645196520000, "n": 7}, {"v": 11, "vw": 0.0336, "o": 0.04, "c": 0.04, "h": 0.04, "l": 0.03, "t": 1645196580000, "n": 6}, {"v": 15, "vw": 0.0393, "o": 0.03, "c": 0.04, "h": 0.04, "l": 0.03, "t": 1645196640000, "n": 3}, {"v": 48, "vw": 0.0369, "o": 0.03, "c": 0.04, "h": 0.04, "l": 0.03, "t": 1645196700000, "n": 4}, {"v": 26, "vw": 0.0308, "o": 0.03, "c": 0.04, "h": 0.04, "l": 0.03, "t": 1645196760000, "n": 6}, {"v": 45, "vw": 0.03, "o": 0.03, "c": 0.03, "h": 0.03, "l": 0.03, "t": 1645196820000, "n": 5}, {"v": 47, "vw": 0.03, "o": 0.03, "c": 0.03, "h": 0.03, "l": 0.03, "t": 1645196880000, "n": 6}, {"v": 7, "vw": 0.02, "o": 0.02, "c": 0.02, "h": 0.02, "l": 0.02, "t": 1645196940000, "n": 2}, {"v": 59, "vw": 0.0297, "o": 0.03, "c": 0.02, "h": 0.03, "l": 0.02, "t": 1645197000000, "n": 8}, {"v": 9, "vw": 0.0233, "o": 0.02, "c": 0.03, "h": 0.03, "l": 0.02, "t": 1645197120000, "n": 3}, {"v": 32, "vw": 0.0288, "o": 0.03, "c": 0.02, "h": 0.03, "l": 0.02, "t": 1645197180000, "n": 5}, {"v": 256, "vw": 0.0296, "o": 0.02, "c": 0.03, "h": 0.03, "l": 0.02, "t": 1645197240000, "n": 8}, {"v": 38, "vw": 0.0303, "o": 0.01, "c": 0.02, "h": 0.04, "l": 0.01, "t": 1645197300000, "n": 8}, {"v": 51, "vw": 0.0225, "o": 0.03, "c": 0.02, "h": 0.04, "l": 0.02, "t": 1645197360000, "n": 7}, {"v": 6, "vw": 0.02, "o": 0.02, "c": 0.02, "h": 0.02, "l": 0.02, "t": 1645197420000, "n": 3}, {"v": 11, "vw": 0.0209, "o": 0.03, "c": 0.02, "h": 0.03, "l": 0.02, "t": 1645197480000, "n": 2}, {"v": 48, "vw": 0.029, "o": 0.03, "c": 0.02, "h": 0.03, "l": 0.02, "t": 1645197540000, "n": 5}, {"v": 16, "vw": 0.0231, "o": 0.03, "c": 0.02, "h": 0.03, "l": 0.02, "t": 1645197600000, "n": 5}, {"v": 107, "vw": 0.0247, "o": 0.03, "c": 0.02, "h": 0.03, "l": 0.02, "t": 1645197660000, "n": 8}, {"v": 26, "vw": 0.0269, "o": 0.02, "c": 0.03, "h": 0.03, "l": 0.02, "t": 1645197720000, "n": 4}, {"v": 1, "vw": 0.02, "o": 0.02, "c": 0.02, "h": 0.02, "l": 0.02, "t": 1645197780000, "n": 1}, {"v": 47, "vw": 0.0202, "o": 0.02, "c": 0.03, "h": 0.03, "l": 0.02, "t": 1645197840000, "n": 7}, {"v": 5, "vw": 0.02, "o": 0.02, "c": 0.02, "h": 0.02, "l": 0.02, "t": 1645197900000, "n": 1}, {"v": 5, "vw": 0.022, "o": 0.02, "c": 0.03, "h": 0.03, "l": 0.02, "t": 1645197960000, "n": 5}, {"v": 3, "vw": 0.0267, "o": 0.02, "c": 0.03, "h": 0.03, "l": 0.02, "t": 1645198020000, "n": 3}, {"v": 1, "vw": 0.03, "o": 0.03, "c": 0.03, "h": 0.03, "l": 0.03, "t": 1645198080000, "n": 1}, {"v": 129, "vw": 0.0202, "o": 0.03, "c": 0.01, "h": 0.04, "l": 0.01, "t": 1645198140000, "n": 19}, {"v": 8, "vw": 0.0163, "o": 0.01, "c": 0.01, "h": 0.02, "l": 0.01, "t": 1645198200000, "n": 4}, {"v": 2, "vw": 0.01, "o": 0.01, "c": 0.01, "h": 0.01, "l": 0.01, "t": 1645198260000, "n": 2}, {"v": 166, "vw": 0.0101, "o": 0.01, "c": 0.01, "h": 0.02, "l": 0.01, "t": 1645198320000, "n": 5}, {"v": 9, "vw": 0.0178, "o": 0.01, "c": 0.02, "h": 0.02, "l": 0.01, "t": 1645198380000, "n": 6}, {"v": 2, "vw": 0.015, "o": 0.01, "c": 0.02, "h": 0.02, "l": 0.01, "t": 1645198440000, "n": 2}, {"v": 6, "vw": 0.02, "o": 0.02, "c": 0.02, "h": 0.02, "l": 0.02, "t": 1645198500000, "n": 3}, {"v": 2, "vw": 0.02, "o": 0.02, "c": 0.02, "h": 0.02, "l": 0.02, "t": 1645198560000, "n": 1}, {"v": 1, "vw": 0.01, "o": 0.01, "c": 0.01, "h": 0.01, "l": 0.01, "t": 1645198620000, "n": 1}, {"v": 19, "vw": 0.0163, "o": 0.01, "c": 0.02, "h": 0.02, "l": 0.01, "t": 1645198680000, "n": 8}, {"v": 6, "vw": 0.0183, "o": 0.01, "c": 0.02, "h": 0.02, "l": 0.01, "t": 1645198740000, "n": 2}, {"v": 8, "vw": 0.0163, "o": 0.02, "c": 0.01, "h": 0.02, "l": 0.01, "t": 1645198800000, "n": 3}, {"v": 5, "vw": 0.014, "o": 0.02, "c": 0.02, "h": 0.02, "l": 0.01, "t": 1645198860000, "n": 5}, {"v": 24, "vw": 0.0192, "o": 0.01, "c": 0.02, "h": 0.02, "l": 0.01, "t": 1645198920000, "n": 3}, {"v": 2, "vw": 0.01, "o": 0.01, "c": 0.01, "h": 0.01, "l": 0.01, "t": 1645198980000, "n": 2}, {"v": 201, "vw": 0.01, "o": 0.02, "c": 0.01, "h": 0.02, "l": 0.01, "t": 1645199040000, "n": 3}, {"v": 926, "vw": 0.0102, "o": 0.02, "c": 0.01, "h": 0.02, "l": 0.01, "t": 1645199100000, "n": 4}, {"v": 5, "vw": 0.012, "o": 0.02, "c": 0.01, "h": 0.02, "l": 0.01, "t": 1645199220000, "n": 3}, {"v": 7, "vw": 0.0129, "o": 0.02, "c": 0.01, "h": 0.02, "l": 0.01, "t": 1645199340000, "n": 6}, {"v": 3, "vw": 0.01, "o": 0.01, "c": 0.01, "h": 0.01, "l": 0.01, "t": 1645199400000, "n": 2}, {"v": 228, "vw": 0.01, "o": 0.01, "c": 0.01, "h": 0.02, "l": 0.01, "t": 1645199460000, "n": 8}, {"v": 18, "vw": 0.0128, "o": 0.02, "c": 0.01, "h": 0.02, "l": 0.01, "t": 1645199520000, "n": 2}, {"v": 1, "vw": 0.01, "o": 0.01, "c": 0.01, "h": 0.01, "l": 0.01, "t": 1645199580000, "n": 1}, {"v": 29, "vw": 0.01, "o": 0.01, "c": 0.01, "h": 0.01, "l": 0.01, "t": 1645199640000, "n": 3}, {"v": 1, "vw": 0.01, "o": 0.01, "c": 0.01, "h": 0.01, "l": 0.01, "t": 1645199700000, "n": 1}, {"v": 4, "vw": 0.015, "o": 0.01, "c": 0.02, "h": 0.02, "l": 0.01, "t": 1645199760000, "n": 2}, {"v": 7, "vw": 0.01, "o": 0.01, "c": 0.01, "h": 0.01, "l": 0.01, "t": 1645199880000, "n": 2}, {"v": 8, "vw": 0.0175, "o": 0.01, "c": 0.01, "h": 0.02, "l": 0.01, "t": 1645199940000, "n": 3}, {"v": 43, "vw": 0.0102, "o": 0.01, "c": 0.01, "h": 0.02, "l": 0.01, "t": 1645200000000, "n": 6}, {"v": 20, "vw": 0.01, "o": 0.01, "c": 0.01, "h": 0.01, "l": 0.01, "t": 1645200060000, "n": 3}, {"v": 10, "vw": 0.018, "o": 0.01, "c": 0.02, "h": 0.02, "l": 0.01, "t": 1645200120000, "n": 4}, {"v": 13, "vw": 0.0115, "o": 0.01, "c": 0.02, "h": 0.02, "l": 0.01, "t": 1645200180000, "n": 3}, {"v": 11, "vw": 0.01, "o": 0.01, "c": 0.01, "h": 0.01, "l": 0.01, "t": 1645200300000, "n": 5}, {"v": 6, "vw": 0.015, "o": 0.01, "c": 0.01, "h": 0.02, "l": 0.01, "t": 1645200360000, "n": 4}, {"v": 20, "vw": 0.01, "o": 0.01, "c": 0.01, "h": 0.01, "l": 0.01, "t": 1645200420000, "n": 1}, {"v": 1, "vw": 0.02, "o": 0.02, "c": 0.02, "h": 0.02, "l": 0.02, "t": 1645200480000, "n": 1}, {"v": 100, "vw": 0.01, "o": 0.01, "c": 0.01, "h": 0.01, "l": 0.01, "t": 1645200600000, "n": 1}, {"v": 12, "vw": 0.01, "o": 0.01, "c": 0.01, "h": 0.01, "l": 0.01, "t": 1645200660000, "n": 4}, {"v": 4, "vw": 0.0175, "o": 0.02, "c": 0.01, "h": 0.02, "l": 0.01, "t": 1645200720000, "n": 2}, {"v": 2, "vw": 0.01, "o": 0.01, "c": 0.01, "h": 0.01, "l": 0.01, "t": 1645200780000, "n": 1}, {"v": 200, "vw": 0.01, "o": 0.01, "c": 0.01, "h": 0.01, "l": 0.01, "t": 1645200840000, "n": 4}, {"v": 11, "vw": 0.01, "o": 0.01, "c": 0.01, "h": 0.01, "l": 0.01, "t": 1645200900000, "n": 1}, {"v": 2, "vw": 0.01, "o": 0.01, "c": 0.01, "h": 0.01, "l": 0.01, "t": 1645200960000, "n": 1}, {"v": 4, "vw": 0.0125, "o": 0.02, "c": 0.01, "h": 0.02, "l": 0.01, "t": 1645201020000, "n": 2}, {"v": 1, "vw": 0.01, "o": 0.01, "c": 0.01, "h": 0.01, "l": 0.01, "t": 1645201080000, "n": 1}, {"v": 42, "vw": 0.01, "o": 0.01, "c": 0.01, "h": 0.01, "l": 0.01, "t": 1645201140000, "n": 4}, {"v": 4, "vw": 0.0125, "o": 0.01, "c": 0.01, "h": 0.02, "l": 0.01, "t": 1645201200000, "n": 4}, {"v": 1, "vw": 0.02, "o": 0.02, "c": 0.02, "h": 0.02, "l": 0.02, "t": 1645201320000, "n": 1}, {"v": 11, "vw": 0.01, "o": 0.01, "c": 0.01, "h": 0.01, "l": 0.01, "t": 1645201380000, "n": 4}, {"v": 5, "vw": 0.01, "o": 0.01, "c": 0.01, "h": 0.01, "l": 0.01, "t": 1645201440000, "n": 3}, {"v": 50, "vw": 0.01, "o": 0.01, "c": 0.01, "h": 0.01, "l": 0.01, "t": 1645201500000, "n": 1}, {"v": 12, "vw": 0.01, "o": 0.01, "c": 0.01, "h": 0.01, "l": 0.01, "t": 1645201560000, "n": 3}, {"v": 1, "vw": 0.01, "o": 0.01, "c": 0.01, "h": 0.01, "l": 0.01, "t": 1645201620000, "n": 1}, {"v": 1, "vw": 0.01, "o": 0.01, "c": 0.01, "h": 0.01, "l": 0.01, "t": 1645201740000, "n": 1}, {"v": 1, "vw": 0.02, "o": 0.02, "c": 0.02, "h": 0.02, "l": 0.02, "t": 1645201800000, "n": 1}, {"v": 153, "vw": 0.01, "o": 0.01, "c": 0.01, "h": 0.01, "l": 0.01, "t": 1645201860000, "n": 8}, {"v": 2, "vw": 0.01, "o": 0.01, "c": 0.01, "h": 0.01, "l": 0.01, "t": 1645201920000, "n": 1}, {"v": 1, "vw": 0.01, "o": 0.01, "c": 0.01, "h": 0.01, "l": 0.01, "t": 1645201980000, "n": 1}, {"v": 1, "vw": 0.01, "o": 0.01, "c": 0.01, "h": 0.01, "l": 0.01, "t": 1645202040000, "n": 1}, {"v": 14, "vw": 0.02, "o": 0.02, "c": 0.02, "h": 0.02, "l": 0.02, "t": 1645202100000, "n": 1}, {"v": 1, "vw": 0.02, "o": 0.02, "c": 0.02, "h": 0.02, "l": 0.02, "t": 1645202160000, "n": 1}, {"v": 35, "vw": 0.01, "o": 0.01, "c": 0.01, "h": 0.01, "l": 0.01, "t": 1645202220000, "n": 4}, {"v": 15, "vw": 0.0113, "o": 0.01, "c": 0.02, "h": 0.02, "l": 0.01, "t": 1645202280000, "n": 2}, {"v": 2, "vw": 0.02, "o": 0.02, "c": 0.02, "h": 0.02, "l": 0.02, "t": 1645202340000, "n": 1}, {"v": 15, "vw": 0.0193, "o": 0.02, "c": 0.01, "h": 0.02, "l": 0.01, "t": 1645202460000, "n": 2}, {"v": 6, "vw": 0.02, "o": 0.02, "c": 0.02, "h": 0.02, "l": 0.02, "t": 1645202580000, "n": 2}, {"v": 18, "vw": 0.0183, "o": 0.01, "c": 0.02, "h": 0.02, "l": 0.01, "t": 1645202640000, "n": 2}, {"v": 1, "vw": 0.01, "o": 0.01, "c": 0.01, "h": 0.01, "l": 0.01, "t": 1645202700000, "n": 1}, {"v": 2, "vw": 0.01, "o": 0.01, "c": 0.01, "h": 0.01, "l": 0.01, "t": 1645202760000, "n": 2}, {"v": 1, "vw": 0.02, "o": 0.02, "c": 0.02, "h": 0.02, "l": 0.02, "t": 1645202820000, "n": 1}, {"v": 2, "vw": 0.01, "o": 0.01, "c": 0.01, "h": 0.01, "l": 0.01, "t": 1645203060000, "n": 2}, {"v": 1, "vw": 0.02, "o": 0.02, "c": 0.02, "h": 0.02, "l": 0.02, "t": 1645203180000, "n": 1}, {"v": 2, "vw": 0.02, "o": 0.02, "c": 0.02, "h": 0.02, "l": 0.02, "t": 1645203240000, "n": 1}, {"v": 2, "vw": 0.01, "o": 0.01, "c": 0.01, "h": 0.01, "l": 0.01, "t": 1645203360000, "n": 2}, {"v": 2, "vw": 0.01, "o": 0.01, "c": 0.01, "h": 0.01, "l": 0.01, "t": 1645203480000, "n": 1}, {"v": 8, "vw": 0.01, "o": 0.01, "c": 0.01, "h": 0.01, "l": 0.01, "t": 1645203600000, "n": 2}, {"v": 27, "vw": 0.01, "o": 0.01, "c": 0.01, "h": 0.01, "l": 0.01, "t": 1645203780000, "n": 5}, {"v": 27, "vw": 0.01, "o": 0.01, "c": 0.01, "h": 0.01, "l": 0.01, "t": 1645203840000, "n": 2}, {"v": 9, "vw": 0.0156, "o": 0.01, "c": 0.01, "h": 0.02, "l": 0.01, "t": 1645203960000, "n": 4}, {"v": 51, "vw": 0.01, "o": 0.01, "c": 0.01, "h": 0.01, "l": 0.01, "t": 1645204080000, "n": 2}, {"v": 5, "vw": 0.01, "o": 0.01, "c": 0.01, "h": 0.01, "l": 0.01, "t": 1645204140000, "n": 2}, {"v": 7, "vw": 0.01, "o": 0.01, "c": 0.01, "h": 0.01, "l": 0.01, "t": 1645204200000, "n": 3}, {"v": 3, "vw": 0.01, "o": 0.01, "c": 0.01, "h": 0.01, "l": 0.01, "t": 1645204260000, "n": 2}, {"v": 8, "vw": 0.01, "o": 0.01, "c": 0.01, "h": 0.01, "l": 0.01, "t": 1645204440000, "n": 1}, {"v": 1, "vw": 0.01, "o": 0.01, "c": 0.01, "h": 0.01, "l": 0.01, "t": 1645204500000, "n": 1}, {"v": 2, "vw": 0.01, "o": 0.01, "c": 0.01, "h": 0.01, "l": 0.01, "t": 1645204560000, "n": 1}, {"v": 4, "vw": 0.01, "o": 0.01, "c": 0.01, "h": 0.01, "l": 0.01, "t": 1645204800000, "n": 2}, {"v": 10, "vw": 0.01, "o": 0.01, "c": 0.01, "h": 0.01, "l": 0.01, "t": 1645205040000, "n": 1}, {"v": 1, "vw": 0.01, "o": 0.01, "c": 0.01, "h": 0.01, "l": 0.01, "t": 1645205100000, "n": 1}, {"v": 101, "vw": 0.01, "o": 0.01, "c": 0.01, "h": 0.01, "l": 0.01, "t": 1645205160000, "n": 7}, {"v": 10, "vw": 0.01, "o": 0.01, "c": 0.01, "h": 0.01, "l": 0.01, "t": 1645205460000, "n": 1}, {"v": 31, "vw": 0.01, "o": 0.01, "c": 0.01, "h": 0.01, "l": 0.01, "t": 1645205640000, "n": 2}, {"v": 1, "vw": 0.01, "o": 0.01, "c": 0.01, "h": 0.01, "l": 0.01, "t": 1645205940000, "n": 1}, {"v": 70, "vw": 0.01, "o": 0.01, "c": 0.01, "h": 0.01, "l": 0.01, "t": 1645206000000, "n": 2}, {"v": 1, "vw": 0.01, "o": 0.01, "c": 0.01, "h": 0.01, "l": 0.01, "t": 1645206180000, "n": 1}, {"v": 6, "vw": 0.01, "o": 0.01, "c": 0.01, "h": 0.01, "l": 0.01, "t": 1645206240000, "n": 2}, {"v": 3, "vw": 0.01, "o": 0.01, "c": 0.01, "h": 0.01, "l": 0.01, "t": 1645206420000, "n": 2}, {"v": 2, "vw": 0.01, "o": 0.01, "c": 0.01, "h": 0.01, "l": 0.01, "t": 1645206480000, "n": 2}, {"v": 16, "vw": 0.01, "o": 0.01, "c": 0.01, "h": 0.01, "l": 0.01, "t": 1645206600000, "n": 3}, {"v": 20, "vw": 0.01, "o": 0.01, "c": 0.01, "h": 0.01, "l": 0.01, "t": 1645206660000, "n": 3}, {"v": 100, "vw": 0.01, "o": 0.01, "c": 0.01, "h": 0.01, "l": 0.01, "t": 1645206960000, "n": 1}, {"v": 1, "vw": 0.01, "o": 0.01, "c": 0.01, "h": 0.01, "l": 0.01, "t": 1645207080000, "n": 1}, {"v": 1, "vw": 0.01, "o": 0.01, "c": 0.01, "h": 0.01, "l": 0.01, "t": 1645207140000, "n": 1}, {"v": 1, "vw": 0.01, "o": 0.01, "c": 0.01, "h": 0.01, "l": 0.01, "t": 1645207200000, "n": 1}, {"v": 1, "vw": 0.01, "o": 0.01, "c": 0.01, "h": 0.01, "l": 0.01, "t": 1645207320000, "n": 1}, {"v": 16, "vw": 0.01, "o": 0.01, "c": 0.01, "h": 0.01, "l": 0.01, "t": 1645207380000, "n": 1}, {"v": 30, "vw": 0.01, "o": 0.01, "c": 0.01, "h": 0.01, "l": 0.01, "t": 1645207560000, "n": 3}, {"v": 2, "vw": 0.01, "o": 0.01, "c": 0.01, "h": 0.01, "l": 0.01, "t": 1645207620000, "n": 1}, {"v": 4, "vw": 0.01, "o": 0.01, "c": 0.01, "h": 0.01, "l": 0.01, "t": 1645208100000, "n": 4}, {"v": 11, "vw": 0.01, "o": 0.01, "c": 0.01, "h": 0.01, "l": 0.01, "t": 1645208760000, "n": 1}, {"v": 2, "vw": 0.01, "o": 0.01, "c": 0.01, "h": 0.01, "l": 0.01, "t": 1645209180000, "n": 1}, {"v": 2, "vw": 0.01, "o": 0.01, "c": 0.01, "h": 0.01, "l": 0.01, "t": 1645209240000, "n": 1}, {"v": 4, "vw": 0.01, "o": 0.01, "c": 0.01, "h": 0.01, "l": 0.01, "t": 1645209480000, "n": 3}, {"v": 1, "vw": 0.01, "o": 0.01, "c": 0.01, "h": 0.01, "l": 0.01, "t": 1645209540000, "n": 1}, {"v": 1, "vw": 0.01, "o": 0.01, "c": 0.01, "h": 0.01, "l": 0.01, "t": 1645209960000, "n": 1}, {"v": 1, "vw": 0.01, "o": 0.01, "c": 0.01, "h": 0.01, "l": 0.01, "t": 1645210740000, "n": 1}, {"v": 5, "vw": 0.01, "o": 0.01, "c": 0.01, "h": 0.01, "l": 0.01, "t": 1645210860000, "n": 1}, {"v": 2, "vw": 0.01, "o": 0.01, "c": 0.01, "h": 0.01, "l": 0.01, "t": 1645211520000, "n": 1}, {"v": 1, "vw": 0.01, "o": 0.01, "c": 0.01, "h": 0.01, "l": 0.01, "t": 1645212060000, "n": 1}, {"v": 50, "vw": 0.01, "o": 0.01, "c": 0.01, "h": 0.01, "l": 0.01, "t": 1645212420000, "n": 1}, {"v": 17, "vw": 0.01, "o": 0.01, "c": 0.01, "h": 0.01, "l": 0.01, "t": 1645212600000, "n": 3}, {"v": 1, "vw": 0.01, "o": 0.01, "c": 0.01, "h": 0.01, "l": 0.01, "t": 1645213200000, "n": 1}, {"v": 2, "vw": 0.01, "o": 0.01, "c": 0.01, "h": 0.01, "l": 0.01, "t": 1645213320000, "n": 1}, {"v": 1, "vw": 0.01, "o": 0.01, "c": 0.01, "h": 0.01, "l": 0.01, "t": 1645213620000, "n": 1}, {"v": 9, "vw": 0.01, "o": 0.01, "c": 0.01, "h": 0.01, "l": 0.01, "t": 1645213860000, "n": 1}, {"v": 2, "vw": 0.01, "o": 0.01, "c": 0.01, "h": 0.01, "l": 0.01, "t": 1645213980000, "n": 2}, {"v": 29, "vw": 0.01, "o": 0.01, "c": 0.01, "h": 0.01, "l": 0.01, "t": 1645214160000, "n": 2}, {"v": 2, "vw": 0.01, "o": 0.01, "c": 0.01, "h": 0.01, "l": 0.01, "t": 1645214580000, "n": 1}, {"v": 6, "vw": 0.01, "o": 0.01, "c": 0.01, "h": 0.01, "l": 0.01, "t": 1645214760000, "n": 1}, {"v": 5, "vw": 0.01, "o": 0.01, "c": 0.01, "h": 0.01, "l": 0.01, "t": 1645215120000, "n": 1}, {"v": 25, "vw": 0.01, "o": 0.01, "c": 0.01, "h": 0.01, "l": 0.01, "t": 1645215300000, "n": 1}, {"v": 1, "vw": 0.01, "o": 0.01, "c": 0.01, "h": 0.01, "l": 0.01, "t": 1645215660000, "n": 1}, {"v": 3, "vw": 0.01, "o": 0.01, "c": 0.01, "h": 0.01, "l": 0.01, "t": 1645215720000, "n": 3}, {"v": 34, "vw": 0.01, "o": 0.01, "c": 0.01, "h": 0.01, "l": 0.01, "t": 1645217220000, "n": 1}, {"v": 4, "vw": 0.01, "o": 0.01, "c": 0.01, "h": 0.01, "l": 0.01, "t": 1645217820000, "n": 1}], "status": "OK", "request_id": "6716303200cd31c9f30bda05b34c2bca", "count": 193}